{"busqueda": "Samsung Galaxy Tab","articulo":"articulo1"}
{"busqueda": "Microsoft Surface Go LTE","articulo":"articulo2"}
{"busqueda": "Rosewill THOR","articulo":"articulo3"}
{"busqueda": "Rosewill RGB","articulo":"articulo4"}
{"busqueda": "Reloj Cronógrafo","articulo":"articulo5"}
{"busqueda": "Silpada","articulo":"articulo6"}
{"busqueda": "Perfume","articulo":"articulo7"}
{"busqueda": "afeitadora eléctrica","articulo":"articulo8"}
{"busqueda": "Motorcycle Cover","articulo":"articulo9"}
{"busqueda": "Llavero","articulo":"articulo10"}
{"busqueda": "Dragon Ball Super","articulo":"articulo11"}
{"busqueda": "Call of Duty Zombies","articulo":"articulo12"}
{"busqueda": "microscopio","articulo":"articulo13"}
{"busqueda": "Dental intraoral","articulo":"articulo14"}
{"busqueda": "Bicicleta","articulo":"articulo15"}
{"busqueda": "Demarini","articulo":"articulo16"}
{"busqueda": "colchón","articulo":"articulo17"}
{"busqueda": "ensores","articulo":"articulo18"}